pyggle/__init__.py
pyggle/boggle.py
pyggle/functions.py
pyggle/data/words_alpha.txt
pyggle-1.2.0.dist-info/licenses/LICENSE
pyggle-1.2.0.dist-info/METADATA
pyggle-1.2.0.dist-info/WHEEL
pyggle-1.2.0.dist-info/top_level.txt
pyggle-1.2.0.dist-info/RECORD
