Metadata-Version: 2.4
Name: pyggle
Version: 1.2.0
Summary: Python-based package that allows you to solve any N x M Boggle board.
Home-page: https://github.com/andrearcaina/pyggle
Author: Andre Arcaina
Author-email: dtandre331@gmail.com
License: MIT
Requires-Python: >=3.6
License-File: LICENSE
Dynamic: author
Dynamic: author-email
Dynamic: description
Dynamic: description-content-type
Dynamic: home-page
Dynamic: license
Dynamic: license-file
Dynamic: requires-python
Dynamic: summary
